Metadata-Version: 2.1
Name: funcargparse
Version: 0.2.4
Summary: Create an argparse.ArgumentParser from function docstrings
Home-page: https://github.com/Chilipp/funcargparse
Author: Philipp S. Sommer
Author-email: philipp.sommer@hereon.de
License: Apache-2.0
Project-URL: Documentation, https://funcargparse.readthedocs.io
Project-URL: Source, https://github.com/Chilipp/psyplot
Project-URL: Tracker, https://github.com/Chilipp/funcargparse/issues
Keywords: argparse re docrep
Platform: UNKNOWN
Classifier: Development Status :: 5 - Production/Stable
Classifier: Intended Audience :: Developers
Classifier: Topic :: Documentation
Classifier: License :: OSI Approved :: GNU General Public License v2 (GPLv2)
Classifier: Programming Language :: Python :: 2
Classifier: Programming Language :: Python :: 2.7
Classifier: Programming Language :: Python :: 3
Classifier: Programming Language :: Python :: 3.5
Classifier: Programming Language :: Python :: 3.6
Classifier: Programming Language :: Python :: 3.7
Classifier: Programming Language :: Python :: 3.8
Classifier: Operating System :: OS Independent
